{
    "action": [
        {
            "action_type": "UNIT_REMOVE_ABILITY", 
            "args_list": [
                {
                    "arg_type": 100006, 
                    "args_list": [
                        [
                            "UNIT_ENTITY", 
                            "玩家英雄数组"
                        ], 
                        {
                            "arg_type": 100002, 
                            "args_list": [
                                {
                                    "arg_type": 100025, 
                                    "args_list": [
                                        {
                                            "__tuple__": true, 
                                            "items": [
                                                "PLAYER", 
                                                "ai玩家", 
                                                "local"
                                            ]
                                        }
                                    ], 
                                    "sub_type": "VARIABLE"
                                }
                            ], 
                            "sub_type": "PLAYER_ID_NUMBER"
                        }
                    ], 
                    "sub_type": 11
                }, 
                {
                    "arg_type": 100182, 
                    "args_list": [
                        3
                    ], 
                    "sub_type": 1
                }, 
                {
                    "arg_type": 100002, 
                    "args_list": [
                        {
                            "__tuple__": true, 
                            "items": [
                                "INTEGER", 
                                "坑位", 
                                "local"
                            ]
                        }
                    ], 
                    "sub_type": 6
                }
            ], 
            "bp": false, 
            "element_id": 8746107970015, 
            "enable": true
        }, 
        {
            "action_type": "SET_VARIABLE", 
            "args_list": [
                {
                    "arg_type": 100030, 
                    "args_list": [
                        {
                            "__tuple__": true, 
                            "items": [
                                "INTEGER", 
                                "随机到的技能索引", 
                                "local"
                            ]
                        }
                    ], 
                    "sub_type": 1
                }, 
                {
                    "arg_type": 100002, 
                    "args_list": [
                        {
                            "arg_type": 100201, 
                            "args_list": [
                                {
                                    "__tuple__": true, 
                                    "items": [
                                        "RANDOM_POOL", 
                                        "小技能随机池"
                                    ]
                                }, 
                                {
                                    "arg_type": 100002, 
                                    "args_list": [
                                        {
                                            "arg_type": 100025, 
                                            "args_list": [
                                                {
                                                    "__tuple__": true, 
                                                    "items": [
                                                        "PLAYER", 
                                                        "ai玩家", 
                                                        "local"
                                                    ]
                                                }
                                            ], 
                                            "sub_type": "VARIABLE"
                                        }
                                    ], 
                                    "sub_type": "PLAYER_ID_NUMBER"
                                }
                            ], 
                            "sub_type": 3
                        }
                    ], 
                    "op_arg": [
                        {
                            "arg_type": 100001, 
                            "args_list": [
                                true
                            ], 
                            "sub_type": 1
                        }
                    ], 
                    "op_arg_enable": [
                        false
                    ], 
                    "sub_type": "GET_BITRARY_RANDOM_POOL_VALUE"
                }
            ], 
            "bp": false, 
            "element_id": 18148314770060, 
            "enable": true
        }, 
        {
            "action_type": "UNIT_ADD_ABILITY", 
            "args_list": [
                {
                    "arg_type": 100006, 
                    "args_list": [
                        [
                            "UNIT_ENTITY", 
                            "玩家英雄数组"
                        ], 
                        {
                            "arg_type": 100002, 
                            "args_list": [
                                {
                                    "arg_type": 100025, 
                                    "args_list": [
                                        [
                                            "PLAYER", 
                                            "ai玩家", 
                                            "local"
                                        ]
                                    ], 
                                    "sub_type": "VARIABLE"
                                }
                            ], 
                            "sub_type": "PLAYER_ID_NUMBER"
                        }
                    ], 
                    "sub_type": 11
                }, 
                {
                    "arg_type": 100182, 
                    "args_list": [
                        3
                    ], 
                    "sub_type": 1
                }, 
                {
                    "arg_type": 100039, 
                    "args_list": [
                        {
                            "__tuple__": true, 
                            "items": [
                                "ABILITY_NAME", 
                                "技能池（普通）"
                            ]
                        }, 
                        {
                            "arg_type": 100002, 
                            "args_list": [
                                {
                                    "__tuple__": true, 
                                    "items": [
                                        "INTEGER", 
                                        "随机到的技能索引", 
                                        "local"
                                    ]
                                }
                            ], 
                            "sub_type": 6
                        }
                    ], 
                    "sub_type": "VARIABLE"
                }
            ], 
            "bp": false, 
            "element_id": 8746107970039, 
            "enable": true, 
            "op_arg": [
                {
                    "arg_type": 100002, 
                    "args_list": [
                        {
                            "__tuple__": true, 
                            "items": [
                                "INTEGER", 
                                "坑位", 
                                "local"
                            ]
                        }
                    ], 
                    "sub_type": 6
                }, 
                null, 
                null
            ], 
            "op_arg_enable": [
                true, 
                false, 
                false
            ]
        }, 
        {
            "action_type": "PRINT_MESSAGE_ACTION_TO_DIALOG", 
            "args_list": [
                {
                    "arg_type": 100175, 
                    "args_list": [
                        3
                    ], 
                    "sub_type": 1
                }, 
                {
                    "arg_type": 100003, 
                    "args_list": [
                        {
                            "arg_type": 100014, 
                            "args_list": [
                                {
                                    "arg_type": 100006, 
                                    "args_list": [
                                        [
                                            "UNIT_ENTITY", 
                                            "玩家英雄数组"
                                        ], 
                                        {
                                            "arg_type": 100002, 
                                            "args_list": [
                                                {
                                                    "arg_type": 100025, 
                                                    "args_list": [
                                                        [
                                                            "PLAYER", 
                                                            "ai玩家", 
                                                            "local"
                                                        ]
                                                    ], 
                                                    "sub_type": "VARIABLE"
                                                }
                                            ], 
                                            "sub_type": "PLAYER_ID_NUMBER"
                                        }
                                    ], 
                                    "sub_type": 11
                                }, 
                                {
                                    "arg_type": 100182, 
                                    "args_list": [
                                        3
                                    ], 
                                    "sub_type": 1
                                }, 
                                {
                                    "arg_type": 100002, 
                                    "args_list": [
                                        [
                                            "INTEGER", 
                                            "坑位", 
                                            "local"
                                        ]
                                    ], 
                                    "sub_type": 6
                                }
                            ], 
                            "sub_type": "UNIT_ABILITY"
                        }
                    ], 
                    "sub_type": "GET_ABILITY_OBJECT_NAME"
                }
            ], 
            "bp": false, 
            "element_id": 18148314770070, 
            "enable": false
        }, 
        {
            "action_type": "SET_RANDOM_POOL_VALUE", 
            "args_list": [
                {
                    "arg_type": 100201, 
                    "args_list": [
                        [
                            "RANDOM_POOL", 
                            "小技能随机池"
                        ], 
                        {
                            "arg_type": 100002, 
                            "args_list": [
                                {
                                    "arg_type": 100025, 
                                    "args_list": [
                                        [
                                            "PLAYER", 
                                            "ai玩家", 
                                            "local"
                                        ]
                                    ], 
                                    "sub_type": "VARIABLE"
                                }
                            ], 
                            "sub_type": "PLAYER_ID_NUMBER"
                        }
                    ], 
                    "sub_type": 3
                }, 
                {
                    "arg_type": 100002, 
                    "args_list": [
                        {
                            "__tuple__": true, 
                            "items": [
                                "INTEGER", 
                                "随机到的技能索引", 
                                "local"
                            ]
                        }
                    ], 
                    "sub_type": 6
                }, 
                {
                    "arg_type": 100002, 
                    "args_list": [
                        0
                    ], 
                    "sub_type": 1
                }
            ], 
            "bp": false, 
            "element_id": 18148314770068, 
            "enable": true
        }, 
        {
            "action_type": "CALL_TRIGGER_FUNC", 
            "args_list": [
                {
                    "arg_type": 100177, 
                    "args_list": [
                        {
                            "arg_type": 100014, 
                            "args_list": [
                                {
                                    "arg_type": 100006, 
                                    "args_list": [
                                        [
                                            "UNIT_ENTITY", 
                                            "玩家英雄数组"
                                        ], 
                                        {
                                            "arg_type": 100002, 
                                            "args_list": [
                                                {
                                                    "arg_type": 100025, 
                                                    "args_list": [
                                                        [
                                                            "PLAYER", 
                                                            "ai玩家", 
                                                            "local"
                                                        ]
                                                    ], 
                                                    "sub_type": "VARIABLE"
                                                }
                                            ], 
                                            "sub_type": "PLAYER_ID_NUMBER"
                                        }
                                    ], 
                                    "sub_type": 11
                                }, 
                                {
                                    "arg_type": 100182, 
                                    "args_list": [
                                        3
                                    ], 
                                    "sub_type": 1
                                }, 
                                {
                                    "arg_type": 100002, 
                                    "args_list": [
                                        [
                                            "INTEGER", 
                                            "坑位", 
                                            "local"
                                        ]
                                    ], 
                                    "sub_type": 6
                                }
                            ], 
                            "sub_type": "UNIT_ABILITY"
                        }
                    ], 
                    "op_arg": [], 
                    "op_arg_enable": [], 
                    "sub_type": "377ff20f08b811ed8c2b30d042f7e2bd"
                }
            ], 
            "bp": false, 
            "call_rt_arg_idxes": [], 
            "element_id": 16784220670013, 
            "enable": true
        }
    ], 
    "call_enabled": true, 
    "condition": [], 
    "enabled": true, 
    "event": [], 
    "func_category": "t_function", 
    "func_comment": "", 
    "func_des": "为ai{ai玩家}学一个随机小技能放在坑位{坑位}", 
    "func_id": "48843840334811edbfa230d042f7e2bd", 
    "func_name": "AI学技能(小技能）", 
    "func_param_list": [
        {
            "__tuple__": true, 
            "items": [
                "ai玩家", 
                true
            ]
        }, 
        {
            "__tuple__": true, 
            "items": [
                "坑位", 
                true
            ]
        }
    ], 
    "group_id": "xlM-MP5hEeyfrDDQQvfivX", 
    "is_func": true, 
    "is_official_func": false, 
    "p_trigger_id": null, 
    "trigger_id": 1814831477, 
    "trigger_name": "AI学技能(小技能）", 
    "valid": true, 
    "var_data": [
        {
            "INTEGER": {
                "坑位": 0, 
                "随机到的技能索引": 0
            }, 
            "PLAYER": {
                "ai玩家": 0
            }
        }, 
        {
            "ai玩家": 0, 
            "坑位": 0, 
            "随机到的技能索引": 0
        }, 
        [
            "ai玩家", 
            "坑位", 
            "随机到的技能索引"
        ]
    ]
}