{
    "local_variable": {
        "16351236": {
            "variable_dict": {}, 
            "variable_length_dict": {}
        }, 
        "775913473": {
            "variable_dict": {
                "NEW_TIMER": {}, 
                "UNIT_ENTITY": {}, 
                "UNIT_GROUP": {
                    "\u653b\u51fb\u76ee\u6807": []
                }
            }, 
            "variable_length_dict": {
                "\u653b\u51fb\u76ee\u6807": 0
            }
        }, 
        "1730162690": {
            "variable_dict": {}, 
            "variable_length_dict": {}
        }
    }, 
    "trigger_dict": {
        "16351236": {
            "action": [
                {
                    "action_type": "ADD_MODIFIER", 
                    "args_list": [
                        {
                            "arg_type": 100006, 
                            "args_list": [], 
                            "sub_type": "ABILITY_OWNER"
                        }, 
                        {
                            "arg_type": 100046, 
                            "args_list": [
                                134243613
                            ], 
                            "sub_type": 1
                        }
                    ], 
                    "bp": false, 
                    "element_id": 7759134730004, 
                    "enable": true, 
                    "op_arg": [
                        {
                            "arg_type": 100006, 
                            "args_list": [], 
                            "sub_type": "ABILITY_OWNER"
                        }, 
                        {
                            "arg_type": 100014, 
                            "args_list": [], 
                            "sub_type": "CUR_ABILITY"
                        }, 
                        null, 
                        null, 
                        null, 
                        null
                    ], 
                    "op_arg_enable": [
                        true, 
                        true, 
                        false, 
                        false, 
                        false, 
                        false
                    ]
                }
            ], 
            "call_enabled": true, 
            "condition": [], 
            "enabled": false, 
            "event": [
                {
                    "args_list": [
                        {
                            "arg_type": 100006, 
                            "args_list": [], 
                            "sub_type": "ABILITY_OWNER"
                        }, 
                        {
                            "arg_type": 100007, 
                            "args_list": [
                                "ET_REVIVE_UNIT"
                            ], 
                            "sub_type": 1
                        }
                    ], 
                    "element_id": 163512360018, 
                    "enable": true, 
                    "event_type": "SPECIAL_UNIT_EVENT"
                }
            ], 
            "group_id": 134242821, 
            "is_conf": true, 
            "p_trigger_id": 775913473, 
            "trigger_id": 16351236, 
            "trigger_name": "\u5b50\u89e6\u53d1\u5668", 
            "valid": true, 
            "var_data": [
                {}, 
                {}, 
                []
            ]
        }, 
        "775913473": {
            "action": [
                {
                    "action_type": "SET_VARIABLE", 
                    "args_list": [
                        {
                            "arg_type": 100030, 
                            "args_list": [
                                [
                                    "UNIT_ENTITY", 
                                    "\u6280\u80fd\u62e5\u6709\u5355\u4f4d", 
                                    "actor"
                                ]
                            ], 
                            "sub_type": 1
                        }, 
                        {
                            "arg_type": 100006, 
                            "args_list": [], 
                            "sub_type": "ABILITY_OWNER"
                        }
                    ], 
                    "bp": false, 
                    "element_id": 7759134730059, 
                    "enable": false
                }, 
                {
                    "action_type": "ADD_MODIFIER", 
                    "args_list": [
                        {
                            "arg_type": 100006, 
                            "args_list": [], 
                            "sub_type": "ABILITY_OWNER"
                        }, 
                        {
                            "arg_type": 100046, 
                            "args_list": [
                                134243613
                            ], 
                            "sub_type": 1
                        }
                    ], 
                    "bp": false, 
                    "element_id": 7759134730004, 
                    "enable": true, 
                    "op_arg": [
                        {
                            "arg_type": 100006, 
                            "args_list": [], 
                            "sub_type": "ABILITY_OWNER"
                        }, 
                        {
                            "arg_type": 100014, 
                            "args_list": [], 
                            "sub_type": "CUR_ABILITY"
                        }, 
                        null, 
                        null, 
                        null, 
                        null
                    ], 
                    "op_arg_enable": [
                        true, 
                        true, 
                        false, 
                        false, 
                        false, 
                        false
                    ]
                }, 
                16351236
            ], 
            "call_enabled": true, 
            "condition": [], 
            "enabled": true, 
            "event": [
                {
                    "args_list": [], 
                    "element_id": 7759134730048, 
                    "enable": true, 
                    "event_type": "ABILITY_OBTAIN"
                }
            ], 
            "group_id": 134242821, 
            "p_trigger_id": null, 
            "trigger_id": 775913473, 
            "trigger_name": "\u65b0\u5efa\u89e6\u53d1\u5668", 
            "valid": true, 
            "var_data": [
                {
                    "NEW_TIMER": {}, 
                    "UNIT_ENTITY": {}, 
                    "UNIT_GROUP": {
                        "\u653b\u51fb\u76ee\u6807": []
                    }
                }, 
                {
                    "\u653b\u51fb\u76ee\u6807": 0
                }, 
                [
                    "\u653b\u51fb\u76ee\u6807"
                ]
            ]
        }, 
        "1730162690": {
            "action": [
                {
                    "action_type": "REMOVE_BUFF_TYPE", 
                    "args_list": [
                        {
                            "arg_type": 100006, 
                            "args_list": [], 
                            "sub_type": "ABILITY_OWNER"
                        }, 
                        {
                            "arg_type": 100046, 
                            "args_list": [
                                134243613
                            ], 
                            "sub_type": 1
                        }
                    ], 
                    "bp": false, 
                    "element_id": 17301626900002, 
                    "enable": true
                }
            ], 
            "call_enabled": true, 
            "condition": [], 
            "enabled": true, 
            "event": [
                {
                    "args_list": [], 
                    "element_id": 17301626900001, 
                    "enable": true, 
                    "event_type": "ABILITY_LOSE"
                }
            ], 
            "group_id": 134242821, 
            "p_trigger_id": null, 
            "trigger_id": 1730162690, 
            "trigger_name": "\u65b0\u5efa\u89e6\u53d1\u5668_2", 
            "valid": true, 
            "var_data": [
                {}, 
                {}, 
                []
            ]
        }
    }, 
    "trigger_group_info": [
        {
            "__tuple__": true, 
            "items": [
                16351236, 
                "\u5b50\u89e6\u53d1\u5668"
            ]
        }, 
        {
            "_trigger_group_": true, 
            "group": [
                {
                    "__tuple__": true, 
                    "items": [
                        775913473, 
                        "\u65b0\u5efa\u89e6\u53d1\u5668"
                    ]
                }, 
                {
                    "__tuple__": true, 
                    "items": [
                        1730162690, 
                        "\u65b0\u5efa\u89e6\u53d1\u5668_2"
                    ]
                }
            ], 
            "key": 134242821, 
            "name": "134242821"
        }
    ], 
    "trigger_version": "1.2", 
    "variable_dict": {
        "UNIT_ENTITY": {
            "\u6280\u80fd\u62e5\u6709\u5355\u4f4d": 0
        }
    }, 
    "variable_group_info": [
        {
            "__tuple__": true, 
            "items": [
                "\u6280\u80fd\u62e5\u6709\u5355\u4f4d", 
                "(\u6280\u80fd\u62e5\u6709\u5355\u4f4d)"
            ]
        }
    ], 
    "variable_length_dict": {
        "\u6280\u80fd\u62e5\u6709\u5355\u4f4d": 0
    }
}